klippiesncola/__init__.py
klippiesncola/switchtel.py
klippiesncola-0.1.1.dist-info/LICENSE
klippiesncola-0.1.1.dist-info/METADATA
klippiesncola-0.1.1.dist-info/WHEEL
klippiesncola-0.1.1.dist-info/top_level.txt
klippiesncola-0.1.1.dist-info/RECORD
