Metadata-Version: 2.1
Name: klippiesncola
Version: 0.1.1
Summary: Manage company VoIP call logs, recordings and more
Home-page: https://github.com/kearabiloe/klippiesncola
Author: Kearabiloe Ledwaba
Author-email: kearabiloe.ledwaba@gmail.com
License: UNKNOWN
Project-URL: Documentation, https://github.com/kearabiloe/klippiesncola
Project-URL: Bug Reports, https://github.com/kearabiloe/klippiesncola/issues
Project-URL: Source Code, https://github.com/kearabiloe/klippiesncola
Keywords: voip,team,switchtel,trello
Platform: UNKNOWN
Classifier: Development Status :: 5 - Production/Stable
Classifier: Intended Audience :: Developers
Classifier: Topic :: Software Development :: Build Tools
Classifier: Programming Language :: Python :: 3
Classifier: Programming Language :: Python :: 3.6
Classifier: Programming Language :: Python :: 3.7
Classifier: Programming Language :: Python :: 3.8
Classifier: Programming Language :: Python :: 3.9
Classifier: Programming Language :: Python :: 3 :: Only
Classifier: License :: OSI Approved :: MIT License
Classifier: Operating System :: OS Independent
Requires-Python: >=3.6
Provides-Extra: dev
Requires-Dist: check-manifest ; extra == 'dev'
